fuckery/__init__.py
fuckery/__main__.py
fuckery/cli.py
fuckery/constants.py
fuckery/exc.py
fuckery/memory.py
fuckery/parser.py
fuckery/vm.py
fuckery-0.7.2.dist-info/AUTHORS.rst
fuckery-0.7.2.dist-info/LICENSE
fuckery-0.7.2.dist-info/METADATA
fuckery-0.7.2.dist-info/WHEEL
fuckery-0.7.2.dist-info/entry_points.txt
fuckery-0.7.2.dist-info/top_level.txt
fuckery-0.7.2.dist-info/RECORD
