Metadata-Version: 2.1
Name: fuckery
Version: 0.7.2
Summary: Python Brainfuck implementation.
Author-email: William Gibb <williamgibb@gmail.com>
License: BSD
Project-URL: Documentation, https://pyfuckery.readthedocs.io/en/latest/
Project-URL: Repository, https://github.com/williamgibb/pyFuckery
Project-URL: Changelog, https://github.com/williamgibb/pyFuckery/blob/master/CHANGELOG.rst
Classifier: Development Status :: 3 - Alpha
Classifier: Intended Audience :: Developers
Classifier: Intended Audience :: Education
Classifier: Intended Audience :: Information Technology
Classifier: Intended Audience :: Science/Research
Classifier: License :: OSI Approved :: MIT License
Classifier: Operating System :: Unix
Classifier: Operating System :: POSIX
Classifier: Operating System :: Microsoft :: Windows
Classifier: Programming Language :: Other
Classifier: Programming Language :: Python :: 3.11
Classifier: Programming Language :: Python :: Implementation :: CPython
Classifier: Topic :: Software Development :: Interpreters
Requires-Python: >=3.11
License-File: LICENSE
License-File: AUTHORS.rst
Requires-Dist: lark-parser (<0.8.0,>=0.7.2)
Requires-Dist: msgpack (<1.1.0,>=1.0.4)
